acoustic_emission_analysis/__init__.py
acoustic_emission_analysis/core.py
acoustic_emission_analysis/event_detector.c
acoustic_emission_analysis/event_detector.doctest.rst
acoustic_emission_analysis_wfs_to_wav-0.2a0.dist-info/METADATA
acoustic_emission_analysis_wfs_to_wav-0.2a0.dist-info/WHEEL
acoustic_emission_analysis_wfs_to_wav-0.2a0.dist-info/licenses/LICENSE
acoustic_emission_analysis_wfs_to_wav-0.2a0.dist-info/RECORD
